asyncKirara/__init__.py
asyncKirara/card.py
asyncKirara/client.py
asyncKirara/enums.py
asyncKirara/idol.py
asyncKirara/infos.py
asyncKirara/skills.py
asyncKirara-1.3.0.dist-info/LICENSE
asyncKirara-1.3.0.dist-info/METADATA
asyncKirara-1.3.0.dist-info/WHEEL
asyncKirara-1.3.0.dist-info/top_level.txt
asyncKirara-1.3.0.dist-info/RECORD
